Metadata-Version: 2.1
Name: supyr_struct
Version: 1.5.4
Summary: A versatile and extensible binary data parsing/serializing library for Python 3
Home-page: https://github.com/Sigmmma/supyr_struct
Author: Sigmmma
Author-email: MosesBobadilla@gmail.com
License: MIT
Project-URL: Source, https://github.com/Sigmmma/supyr_struct
Project-URL: Funding, https://liberapay.com/MEK/
Keywords: supyr_struct,binary,data structure,parser,serializer,serialize
Platform: POSIX
Platform: Windows
Classifier: Development Status :: 4 - Beta
Classifier: Intended Audience :: Developers
Classifier: License :: OSI Approved :: MIT License
Classifier: Programming Language :: Python
Classifier: Programming Language :: Python :: 3
Classifier: Programming Language :: Python :: 3.5
Classifier: Programming Language :: Python :: 3.6
Classifier: Programming Language :: Python :: 3.7
Classifier: Programming Language :: Python :: 3.8
Classifier: Programming Language :: Python :: 3.9
Classifier: Programming Language :: Python :: 3 :: Only
Provides: supyr_struct
Requires-Python: >=3.5
